README.md
setup.py
chilli_py/BFGS.py
chilli_py/BOYS.py
chilli_py/BasisSet.py
chilli_py/CGBF.py
chilli_py/HGP.py
chilli_py/PGBF.py
chilli_py/RFLO.py
chilli_py/RFLOSIC.py
chilli_py/RFLOSIC_simple.py
chilli_py/RHF.py
chilli_py/RKS.py
chilli_py/RMP2.py
chilli_py/RTDHF.py
chilli_py/UHF.py
chilli_py/UKS.py
chilli_py/__init__.py
chilli_py/alias.py
chilli_py/angular_grid.py
chilli_py/atoms.py
chilli_py/bench.py
chilli_py/constants.py
chilli_py/coulomb.py
chilli_py/dipole.py
chilli_py/exc.py
chilli_py/grids.py
chilli_py/integrals.py
chilli_py/kinetic.py
chilli_py/linalg.py
chilli_py/lj.py
chilli_py/my_io.py
chilli_py/nuclear.py
chilli_py/overlap.py
chilli_py/radial_grid.py
chilli_py/read_basis_g94.py
chilli_py/scf.py
chilli_py/scipy_eigh.py
chilli_py/simple_run.py
chilli_py/spin.py
chilli_py/utils.py
chilli_py/version.py
chilli_py.egg-info/PKG-INFO
chilli_py.egg-info/SOURCES.txt
chilli_py.egg-info/dependency_links.txt
chilli_py.egg-info/not-zip-safe
chilli_py.egg-info/requires.txt
chilli_py.egg-info/top_level.txt
chilli_py/basis/__init__.py
chilli_py/basis/gen_basis.py
chilli_py/benchmarksets/__init__.py
chilli_py/benchmarksets/AE6/AE6.py
chilli_py/benchmarksets/AE6/__init__.py
chilli_py/structs/__init__.py
chilli_py/tests/__init__.py
chilli_py/tests/basic_example.py
chilli_py/tests/bench_dip.py
chilli_py/tests/bench_esp.py
chilli_py/tests/bench_rflo.py
chilli_py/tests/bench_rflosic.py
chilli_py/tests/bench_rhf.py
chilli_py/tests/bench_rhf_hgp.py
chilli_py/tests/bench_rks.py
chilli_py/tests/bench_rmp2.py
chilli_py/tests/bench_rtdhf.py
chilli_py/tests/bench_uhf.py
chilli_py/tests/bench_uks.py
chilli_py/tests/chilli_jl.py
chilli_py/tests/clean.py
chilli_py/tests/debug_rflosic.py
chilli_py/tests/test_guess.py
chilli_py/tests/test_history.py
chilli_py/tests/test_pbe.py
chilli_py/tests/tests.py