Metadata-Version: 2.1
Name: chilli-py
Version: 0.1.0b1
Summary: A pure Python GTO SCF code.
Home-page: https://gitlab.com/nextdft/chilli_py
Author: Sebastian Schwalbe
Author-email: theonov13@gmail.com
License: APACHE2.0
Platform: UNKNOWN
Requires-Python: >=3.6
Provides-Extra: addons
